spotify_bot/__init__.py
spotify_bot/bot.py
spotify_bot-1.0.7.dist-info/LICENSE.txt
spotify_bot-1.0.7.dist-info/METADATA
spotify_bot-1.0.7.dist-info/WHEEL
spotify_bot-1.0.7.dist-info/entry_points.txt
spotify_bot-1.0.7.dist-info/top_level.txt
spotify_bot-1.0.7.dist-info/RECORD
